{
  "type": "object",
  "properties": {
    "object": {
      "type": "string"
    },
    "id": {
      "type": "string"
    },
    "name": {
      "type": "string"
    },
    "html": {
      "type": "string"
    },
    "is_writeable": {
      "type": "boolean"
    },
    "created": {
      "type": "string"
    },
    "updated": {
      "type": "string"
    }
  },
  "additionalProperties": true,
  "default": {
    "object": "string",
    "id": "string",
    "name": "string",
    "html": "string",
    "is_writeable": true,
    "created": "string",
    "updated": "string"
  },
  "$schema": "https://json-schema.org/draft/2020-12/schema"
}